openssl_encrypt/__init__.py
openssl_encrypt/__main__.py
openssl_encrypt/cli.py
openssl_encrypt/crypt.py
openssl_encrypt/crypt_gui.py
openssl_encrypt/post_install.py
openssl_encrypt/version.py
openssl_encrypt/version.py.template
openssl_encrypt/docs/COMPREHENSIVE_SECURITY_AUDIT.md
openssl_encrypt/docs/FUTURE_FEATURES.md
openssl_encrypt/docs/HSM_PLUGIN_GUIDE.md
openssl_encrypt/docs/PORTABLE_MEDIA_DESIGN.md
openssl_encrypt/docs/SECURITY_REVIEW.md
openssl_encrypt/docs/SECURITY_REVIEW_v1.3.0.md
openssl_encrypt/docs/TODO.md
openssl_encrypt/docs/VERSION.md
openssl_encrypt/docs/VERSION_PINNING_POLICY.md
openssl_encrypt/docs/YUBIKEY_SETUP.md
openssl_encrypt/docs/_sidebar.md
openssl_encrypt/docs/algorithm-reference.md
openssl_encrypt/docs/architecture.md
openssl_encrypt/docs/crypto_tool_security_analysis.md
openssl_encrypt/docs/dbus-service.md
openssl_encrypt/docs/dependency-management.md
openssl_encrypt/docs/development-setup.md
openssl_encrypt/docs/keystore-guide.md
openssl_encrypt/docs/metadata-formats.md
openssl_encrypt/docs/security.md
openssl_encrypt/docs/user-guide.md
openssl_encrypt/docs/.idea/workspace.xml
openssl_encrypt/modules/__init__.py
openssl_encrypt/modules/algorithm_warnings.py
openssl_encrypt/modules/balloon.py
openssl_encrypt/modules/benchmark_constants.py
openssl_encrypt/modules/cli_aliases.py
openssl_encrypt/modules/config_analyzer.py
openssl_encrypt/modules/config_wizard.py
openssl_encrypt/modules/crypt_cli.py
openssl_encrypt/modules/crypt_cli_helper.py
openssl_encrypt/modules/crypt_cli_subparser.py
openssl_encrypt/modules/crypt_core.py
openssl_encrypt/modules/crypt_errors.py
openssl_encrypt/modules/crypt_settings.py
openssl_encrypt/modules/crypt_utils.py
openssl_encrypt/modules/crypto_secure_memory.py
openssl_encrypt/modules/dbus_client.py
openssl_encrypt/modules/dbus_service.py
openssl_encrypt/modules/decryption_estimator.py
openssl_encrypt/modules/json_validator.py
openssl_encrypt/modules/keystore_cli.py
openssl_encrypt/modules/keystore_utils.py
openssl_encrypt-1.3.5.dist-info/licenses/LICENSE
openssl_encrypt-1.3.5.dist-info/METADATA
openssl_encrypt-1.3.5.dist-info/WHEEL
openssl_encrypt-1.3.5.dist-info/entry_points.txt
openssl_encrypt-1.3.5.dist-info/top_level.txt
openssl_encrypt-1.3.5.dist-info/RECORD
