Metadata-Version: 2.4
Name: openssl_encrypt
Version: 1.3.5
Summary: A package for secure file encryption and decryption based on modern ciphers using heavy-compute-load chaining of hashing and KDF to generate strong encryption password based on users provided password to ensure secure encryption of files
Home-page: https://gitlab.rm-rf.ch/world/openssl_encrypt
Author: Tobi
Author-email: jahlives@gmx.ch
License: Hippocratic-3.0
Project-URL: Bug Tracker, https://gitlab.rm-rf.ch/world/openssl_encrypt/-/issues
Project-URL: Documentation, https://gitlab.rm-rf.ch/world/openssl_encrypt/-/tree/main/openssl_encrypt/docs
Project-URL: Source Code, https://gitlab.rm-rf.ch/world/openssl_encrypt/-/tree/main/openssl_encrypt
Keywords: encryption,decryption,random-password,secure shredding,security
Classifier: Development Status :: 5 - Production/Stable
Classifier: Intended Audience :: Developers
Classifier: Intended Audience :: End Users/Desktop
Classifier: Intended Audience :: Information Technology
Classifier: Intended Audience :: System Administrators
Classifier: Programming Language :: Python :: 3
Classifier: Programming Language :: Python :: 3.9
Classifier: Programming Language :: Python :: 3.10
Classifier: Programming Language :: Python :: 3.11
Classifier: Programming Language :: Python :: 3.12
Classifier: Programming Language :: Python :: 3.13
Classifier: License :: Other/Proprietary License
Classifier: Topic :: Security
Classifier: Topic :: Security :: Cryptography
Classifier: Topic :: Utilities
Classifier: Operating System :: OS Independent
Requires-Python: >=3.9
License-File: LICENSE
Requires-Dist: argon2-cffi==23.1.0
Requires-Dist: argon2-cffi-bindings==21.2.0
Requires-Dist: blake3==1.0.5
Requires-Dist: cffi==1.17.1
Requires-Dist: cryptography==44.0.3
Requires-Dist: numpy==2.3.2
Requires-Dist: pillow==11.3.0
Requires-Dist: pycparser==2.22
Requires-Dist: pyyaml==6.0.2
Requires-Dist: pyzbar==0.1.9
Requires-Dist: qrcode[pil]==8.2
Requires-Dist: randomx==1.1.10.post3
Requires-Dist: whirlpool-py311==1; python_version >= "3.11"
Provides-Extra: dev
Requires-Dist: annotated-types==0.7.0; extra == "dev"
Requires-Dist: anyio==4.9.0; extra == "dev"
Requires-Dist: astroid==3.3.10; extra == "dev"
Requires-Dist: authlib==1.5.2; extra == "dev"
Requires-Dist: bandit==1.7.10; extra == "dev"
Requires-Dist: black==24.10.0; extra == "dev"
Requires-Dist: build==1.2.2.post1; extra == "dev"
Requires-Dist: certifi==2025.4.26; extra == "dev"
Requires-Dist: cfgv==3.4.0; extra == "dev"
Requires-Dist: charset-normalizer==3.4.2; extra == "dev"
Requires-Dist: click==8.2.1; extra == "dev"
Requires-Dist: coverage[toml]==7.8.1; extra == "dev"
Requires-Dist: dill==0.4.0; extra == "dev"
Requires-Dist: distlib==0.3.9; extra == "dev"
Requires-Dist: dparse==0.6.4; extra == "dev"
Requires-Dist: filelock==3.16.1; extra == "dev"
Requires-Dist: h11==0.16.0; extra == "dev"
Requires-Dist: httpcore==1.0.9; extra == "dev"
Requires-Dist: httpx==0.28.1; extra == "dev"
Requires-Dist: identify==2.6.10; extra == "dev"
Requires-Dist: idna==3.10; extra == "dev"
Requires-Dist: iniconfig==2.1.0; extra == "dev"
Requires-Dist: isort==6.0.1; extra == "dev"
Requires-Dist: jinja2==3.1.6; extra == "dev"
Requires-Dist: joblib==1.5.0; extra == "dev"
Requires-Dist: markdown-it-py==3.0.0; extra == "dev"
Requires-Dist: markupsafe==3.0.2; extra == "dev"
Requires-Dist: marshmallow==4.0.0; extra == "dev"
Requires-Dist: mccabe==0.7.0; extra == "dev"
Requires-Dist: mdurl==0.1.2; extra == "dev"
Requires-Dist: mypy-extensions==1.1.0; extra == "dev"
Requires-Dist: nltk==3.9.1; extra == "dev"
Requires-Dist: nodeenv==1.9.1; extra == "dev"
Requires-Dist: numpy==2.3.3; extra == "dev"
Requires-Dist: packaging==25.0; extra == "dev"
Requires-Dist: pathspec==0.12.1; extra == "dev"
Requires-Dist: pbr==6.1.1; extra == "dev"
Requires-Dist: pillow==10.4.0; extra == "dev"
Requires-Dist: pip-tools==7.4.1; extra == "dev"
Requires-Dist: platformdirs==4.3.8; extra == "dev"
Requires-Dist: pluggy==1.6.0; extra == "dev"
Requires-Dist: pre-commit==3.8.0; extra == "dev"
Requires-Dist: psutil==6.1.1; extra == "dev"
Requires-Dist: pydantic==2.9.2; extra == "dev"
Requires-Dist: pydantic-core==2.23.4; extra == "dev"
Requires-Dist: pygments==2.19.1; extra == "dev"
Requires-Dist: pylint==3.3.7; extra == "dev"
Requires-Dist: pyproject-hooks==1.2.0; extra == "dev"
Requires-Dist: pytest==8.3.5; extra == "dev"
Requires-Dist: pytest-cov==4.1.0; extra == "dev"
Requires-Dist: regex==2024.11.6; extra == "dev"
Requires-Dist: requests==2.32.3; extra == "dev"
Requires-Dist: rich==14.0.0; extra == "dev"
Requires-Dist: ruamel-yaml==0.18.10; extra == "dev"
Requires-Dist: safety==3.5.0; extra == "dev"
Requires-Dist: safety-schemas==0.0.14; extra == "dev"
Requires-Dist: shellingham==1.5.4; extra == "dev"
Requires-Dist: sniffio==1.3.1; extra == "dev"
Requires-Dist: stevedore==5.4.1; extra == "dev"
Requires-Dist: tenacity==9.1.2; extra == "dev"
Requires-Dist: tomlkit==0.13.2; extra == "dev"
Requires-Dist: tqdm==4.67.1; extra == "dev"
Requires-Dist: typer==0.15.3; extra == "dev"
Requires-Dist: typing-extensions==4.13.2; extra == "dev"
Requires-Dist: urllib3==2.4.0; extra == "dev"
Requires-Dist: virtualenv==20.31.2; extra == "dev"
Requires-Dist: wheel==0.45.1; extra == "dev"
Dynamic: author
Dynamic: author-email
Dynamic: classifier
Dynamic: description
Dynamic: description-content-type
Dynamic: home-page
Dynamic: keywords
Dynamic: license
Dynamic: license-file
Dynamic: project-url
Dynamic: provides-extra
Dynamic: requires-dist
Dynamic: requires-python
Dynamic: summary
